simple_cats/__init__.py
simple_cats/cats_model.py
simple_cats/cats_utils/__init__.py
simple_cats/cats_utils/constants.py
simple_cats/cats_utils/utils.py
simple_cats/data/__init__.py
simple_cats/data/dataset.py
simple_cats/data/get_billsum_dataset.py
simple_cats/data/get_dataset.py
simple_cats/data/get_default_dataset.py
simple_cats/data/get_glue_dataset.py
simple_cats/data/get_glue_dataset_classification.py
simple_cats/data/get_openwebtext_dataset.py
simple_cats/data/get_refinedweb_dataset.py
simple_cats/data/get_samsum_dataset_.py
simple_cats/data/get_squad_dataset.py
simple_cats/data/get_sst2_dataset.py
simple_cats/data/get_wikitext_dataset.py
simple_cats/kernels/__init__.py
simple_cats/kernels/sparse_mm.py
simple_cats-0.1.3.dist-info/METADATA
simple_cats-0.1.3.dist-info/WHEEL
simple_cats-0.1.3.dist-info/top_level.txt
simple_cats-0.1.3.dist-info/RECORD
