Metadata-Version: 2.1
Name: simple_cats
Version: 0.1.3
Summary: Python package for CATS paper
Home-page: https://github.com/ScalingIntelligence/CATS
Author: Jeyong Lee, Donghyun Lee, ...
Author-email: je-yong.lee@worc.ox.ac.uk
Classifier: Programming Language :: Python :: 3
Classifier: License :: OSI Approved :: MIT License
Classifier: Operating System :: OS Independent
Requires-Python: >=3.6
Requires-Dist: transformers
Requires-Dist: torch
Requires-Dist: triton
Requires-Dist: accelerate
Requires-Dist: bitsandbytes
Requires-Dist: peft
Requires-Dist: evaluate
